{
  "Parent": "Template_Ymmersive_Melodies",
  "TranslationProperties": {
    "Name": "server.items.Ymmersive_Melodies_Tiny_Drum.name",
    "Description": "server.items.Ymmersive_Melodies_Tiny_Drum.description"
  },
  "Icon": "Icons/ItemsGenerated/Ymmersive_Melodies_Tiny_Drum.png",
  "IconProperties": {
    "Scale": 0.5,
    "Rotation": [
      30.0,
      45.0,
      0.0
    ],
    "Translation": [
      -8.0,
      -15.0
    ]
  },
  "Quality": "Common",
  "Model": "Items/Instruments/Ymmersive_Melodies_Tiny_Drum.blockymodel",
  "Texture": "Items/Instruments/Ymmersive_Melodies_Tiny_Drum.png",
  "PlayerAnimationsId": "Ymmersive_Melodies_Tiny_Drum",
  "Interactions": {
    "Held": {
      "Interactions": [
        {
          "Type": "Ymmersive_Melodies_Melody_Playback",
          "Instrument": "Tiny_Drum"
        }
      ],
      "Cooldown": {
        "SkipCooldownReset": true
      }
    },
    "Secondary": {
      "Interactions": [
        {
          "Type": "OpenCustomUI",
          "Page": {
            "Id": "Ymmersive_Melodies_Selection",
            "Instrument": "Tiny_Drum"
          }
        }
      ]
    }
  },
  "Recipe": {
    "TimeSeconds": 2,
    "Input": [
      {
        "ResourceTypeId": "Wood_Trunk",
        "Quantity": 2
      },
      {
        "ItemId": "Ingredient_Leather_Medium",
        "Quantity": 2
      }
    ],
    "BenchRequirement": [
      {
        "Id": "Workbench",
        "Type": "Crafting",
        "Categories": [
          "Workbench_Tools"
        ]
      }
    ],
    "KnowledgeRequired": false
  }
}
